chunking/__init__.py
chunking/auto.py
chunking/base.py
chunking/cli.py
chunking/controller.py
chunking/models.py
chunking/eval/__init__.py
chunking/mime/__init__.py
chunking/mime/base.py
chunking/mime/mime_pdf.py
chunking/parser/__init__.py
chunking/parser/audio.py
chunking/parser/base.py
chunking/parser/code.py
chunking/parser/csv.py
chunking/parser/dict_list.py
chunking/parser/directory.py
chunking/parser/html.py
chunking/parser/image.py
chunking/parser/md.py
chunking/parser/pandoc_engine.py
chunking/parser/pdf.py
chunking/parser/pptx.py
chunking/parser/text.py
chunking/parser/video.py
chunking/parser/xlsx.py
chunking/parser/fastpdf/__init__.py
chunking/parser/fastpdf/main.py
chunking/parser/fastpdf/pdf_heuristic_parser.py
chunking/parser/fastpdf/pdf_image.py
chunking/parser/fastpdf/pdf_layout_parser.py
chunking/parser/fastpdf/pdf_table.py
chunking/parser/fastpdf/pdf_text.py
chunking/parser/fastpdf/plot.py
chunking/parser/fastpdf/util.py
chunking/split/__init__.py
chunking/split/agentic_chunker.py
chunking/split/lumber_chunker.py
chunking/split/md.py
chunking/split/propositionizer.py
chunking/split/split.py
chunking/split/text.py
chunking/split/toc_builder.py
chunking/split/utils.py
chunking/store/__init__.py
chunking/store/fs.py
chunking/store/memory.py
chunking/util/__init__.py
chunking/util/plot.py
chunking_ai-0.0.2.dist-info/licenses/LICENSE
chunking_ai-0.0.2.dist-info/METADATA
chunking_ai-0.0.2.dist-info/WHEEL
chunking_ai-0.0.2.dist-info/entry_points.txt
chunking_ai-0.0.2.dist-info/top_level.txt
chunking_ai-0.0.2.dist-info/RECORD
