Metadata-Version: 2.4
Name: chunking-ai
Version: 0.0.2
Summary: A fast and light-weight library for ingesting and chunking files
Author-email: trducng <trungduc1992@gmail.com>, tadashi <taprosoft@gmail.com>
Project-URL: Homepage, https://github.com/chunking-ai/chunking
Project-URL: Repository, https://github.com/chunking-ai/chunking
Classifier: Programming Language :: Python :: 3
Classifier: Development Status :: 2 - Pre-Alpha
Requires-Python: >=3.9
License-File: LICENSE
Requires-Dist: llm
Requires-Dist: click
Requires-Dist: numpy
Requires-Dist: pypandoc
Requires-Dist: tree-sitter
Requires-Dist: tqdm
Requires-Dist: python-pptx
Requires-Dist: openpyxl
Requires-Dist: beautifulsoup4
Requires-Dist: tree-sitter-markdown
Provides-Extra: dev
Requires-Dist: coverage; extra == "dev"
Requires-Dist: pytest; extra == "dev"
Requires-Dist: black; extra == "dev"
Requires-Dist: flake8; extra == "dev"
Requires-Dist: mypy; extra == "dev"
Requires-Dist: isort; extra == "dev"
Requires-Dist: pre-commit; extra == "dev"
Requires-Dist: notebook; extra == "dev"
Requires-Dist: ipython; extra == "dev"
Requires-Dist: build; extra == "dev"
Requires-Dist: twine; extra == "dev"
Provides-Extra: pdf
Requires-Dist: pypdfium2; extra == "pdf"
Requires-Dist: img2table; extra == "pdf"
Requires-Dist: pillow; extra == "pdf"
Requires-Dist: rapid-layout; extra == "pdf"
Requires-Dist: chunking-pdftext; extra == "pdf"
Provides-Extra: ocr
Requires-Dist: opencv-contrib-python; extra == "ocr"
Requires-Dist: rapidocr; extra == "ocr"
Requires-Dist: rapid-layout; extra == "ocr"
Requires-Dist: pillow; extra == "ocr"
Provides-Extra: audio
Requires-Dist: openai-whisper; extra == "audio"
Requires-Dist: pydub; extra == "audio"
Provides-Extra: pdf-others
Requires-Dist: docling; extra == "pdf-others"
Requires-Dist: unstructured[pdf]; extra == "pdf-others"
Requires-Dist: sycamore-ai[local-inference]; extra == "pdf-others"
Dynamic: license-file
